<?xml version="1.0" encoding="Windows-1252"?>
<EquipmentData xmlns:xsi="http://www.w3.org/2001/XMLSchema-instance" xmlns:xsd="http://www.w3.org/2001/XMLSchema">
  <m_myType>chassis</m_myType>
  <m_equipmentLevel>1</m_equipmentLevel>
  <m_creditValue>1</m_creditValue>
  <m_damageType>0</m_damageType>
  <m_Owner>player</m_Owner>
  <m_baseValues>
    <float>0</float>
    <float>0</float>
    <float>50</float>
    <float>0</float>
    <float>4</float>
    <float>0</float>
    <float>0</float>
  </m_baseValues>
  <m_ValueModifiers>
    <float>0.25</float>
    <float>0.25</float>
    <float>0</float>
    <float>0.25</float>
    <float>0</float>
    <float>0</float>
    <float>0.25</float>
  </m_ValueModifiers>
</EquipmentData>